{
  "series_name": "리빙_모션베드",
  "product_name": "모어 (리빙 모션베드)",
  "product_id": "living_motion_bed_moa",
  "page_id": 62298,
  "source_url": "https://iloomproduct.fursys.com/?p=62298",
  "fetched_at": "2026-05-11T01:02:50.216Z",
  "total_images": 5,
  "failed": 0,
  "images": [
    {
      "file": "01_1024x669_tab1.png",
      "local_path": "assets/products/리빙_모션베드/01_1024x669_tab1.png",
      "size_kb": 530,
      "src": "https://iloomproduct.fursys.com/wp-content/uploads/2026/03/image-44-1024x669.png",
      "alt": "",
      "w": 1024,
      "h": 669,
      "parent_text": "",
      "grand_text": "",
      "prev_text": "",
      "next_text": "",
      "tab": 1
    },
    {
      "file": "02_606x613_tab1.png",
      "local_path": "assets/products/리빙_모션베드/02_606x613_tab1.png",
      "size_kb": 426,
      "src": "https://iloomproduct.fursys.com/wp-content/uploads/2026/03/image-49.png",
      "alt": "",
      "w": 606,
      "h": 613,
      "parent_text": "SO\nSAND OAK",
      "grand_text": "SO\nSAND OAK",
      "prev_text": "",
      "next_text": "SOSAND OAK",
      "tab": 1
    },
    {
      "file": "03_455x417_tab1.jpg",
      "local_path": "assets/products/리빙_모션베드/03_455x417_tab1.jpg",
      "size_kb": 4,
      "src": "https://iloomproduct.fursys.com/wp-content/uploads/2021/02/%EC%97%86%EB%8A%94%EC%BB%AC%EB%9F%AC-6.jpg",
      "alt": "",
      "w": 455,
      "h": 417,
      "parent_text": "",
      "grand_text": "SO\nSAND OAK",
      "prev_text": "",
      "next_text": "",
      "tab": 1
    },
    {
      "file": "04_994x412_tab1.png",
      "local_path": "assets/products/리빙_모션베드/04_994x412_tab1.png",
      "size_kb": 404,
      "src": "https://iloomproduct.fursys.com/wp-content/uploads/2026/03/image-4-1024x425.png",
      "alt": "",
      "w": 994,
      "h": 412,
      "parent_text": "",
      "grand_text": "타겟 및 기획의도\n\n모어 모션베드는 2대를 함께 배치해도 빈틈없이 완성되는 레이아웃과 수납형 헤드, 협탁 구성으로 정돈된 침실 공간을 제안합니다. 헤드 선반에는 휴대폰, 충전기, 안경, 리모컨 등을 손쉽게 정리하고, 협탁과 멀티데스크를 원하는 곳에 배치하여 취침 전 여유로운 루틴까지 더해주어 더욱 침실환경을 자연스럽게 업그레이드 해줍니다.\n내추럴 우드 감성과 호텔 라이크 무드 속에서, 함께하는 휴식과 각자의 편안함까지 모두 담아낸 모션베드입니다.\n\n색상\nSO\nSAND OAK\n품목리스트\n모어 모션베드 다리형\n모어 모션베드 다리형 SS",
      "prev_text": "",
      "next_text": "",
      "tab": 1
    },
    {
      "file": "05_878x498_tab1.png",
      "local_path": "assets/products/리빙_모션베드/05_878x498_tab1.png",
      "size_kb": 700,
      "src": "https://iloomproduct.fursys.com/wp-content/uploads/2026/03/image-43.png",
      "alt": "",
      "w": 878,
      "h": 498,
      "parent_text": "",
      "grand_text": "타겟 및 기획의도\n\n모어 모션베드는 2대를 함께 배치해도 빈틈없이 완성되는 레이아웃과 수납형 헤드, 협탁 구성으로 정돈된 침실 공간을 제안합니다. 헤드 선반에는 휴대폰, 충전기, 안경, 리모컨 등을 손쉽게 정리하고, 협탁과 멀티데스크를 원하는 곳에 배치하여 취침 전 여유로운 루틴까지 더해주어 더욱 침실환경을 자연스럽게 업그레이드 해줍니다.\n내추럴 우드 감성과 호텔 라이크 무드 속에서, 함께하는 휴식과 각자의 편안함까지 모두 담아낸 모션베드입니다.\n\n색상\nSO\nSAND OAK\n품목리스트\n모어 모션베드 다리형\n모어 모션베드 다리형 SS",
      "prev_text": "",
      "next_text": "",
      "tab": 1
    }
  ]
}